cfcompare/__init__.py
cfcompare/cfcompare.py
cfcompare-1.2.0.dist-info/METADATA
cfcompare-1.2.0.dist-info/WHEEL
cfcompare-1.2.0.dist-info/top_level.txt
cfcompare-1.2.0.dist-info/RECORD
