Metadata-Version: 2.1
Name: cfcompare
Version: 1.2.0
Summary: Tool to compare CF Standard Name versions.
Home-page: UNKNOWN
Author: Harry Singh
Author-email: hsing247@uwo.ca
License: UNKNOWN
Download-URL: https://github.com/HarrySng/cfsntool/archive/v1.0.0.tar.gz
Platform: UNKNOWN
Classifier: Programming Language :: Python :: 3
Classifier: License :: OSI Approved :: MIT License
Classifier: Operating System :: OS Independent
Requires-Python: >=3.7
